README.rst
flask_fanstatic.py
setup.py
Flask_Fanstatic.egg-info/PKG-INFO
Flask_Fanstatic.egg-info/SOURCES.txt
Flask_Fanstatic.egg-info/dependency_links.txt
Flask_Fanstatic.egg-info/requires.txt
Flask_Fanstatic.egg-info/top_level.txt
Flask_Fanstatic.egg-info/zip-safe
test/test_fanstatic.py