Metadata-Version: 1.1
Name: Flask-Fanstatic
Version: 0.2.0
Summary: Flask integration for the Fanstatic resource publishing system.
Home-page: http://github.com/mgood/flask-fanstatic
Author: Matt Good
Author-email: matt@matt-good.net
License: BSD
Platform: any
Classifier: Environment :: Web Environment
Classifier: Intended Audience :: Developers
Classifier: License :: OSI Approved :: BSD License
Classifier: Operating System :: OS Independent
Classifier: Programming Language :: Python
Classifier: Topic :: Internet :: WWW/HTTP :: Dynamic Content
Classifier: Topic :: Software Development :: Libraries :: Python Modules
